komfovent_api/__init__.py
komfovent_api/api.py
komfovent_api/classes.py
komfovent_api/networking.py
komfovent_api-0.0.7.dist-info/LICENSE
komfovent_api-0.0.7.dist-info/METADATA
komfovent_api-0.0.7.dist-info/WHEEL
komfovent_api-0.0.7.dist-info/top_level.txt
komfovent_api-0.0.7.dist-info/RECORD
